ethnicity/__init__.py
ethnicity/ethnicity.py
ethnicity/data/anglo-saxon/first_names/first_names_.txt
ethnicity/data/anglo-saxon/full_names/full_names_.txt
ethnicity/data/anglo-saxon/last_names/last_names_.txt
ethnicity/data/anglo-saxon/last_names_common/last_names_common_.txt
ethnicity/data/arabic/first_names/first_names_.txt
ethnicity/data/arabic/full_names/full_names_.txt
ethnicity/data/arabic/last_names/last_names_.txt
ethnicity/data/balkan/first_names/first_names_.txt
ethnicity/data/balkan/full_names/full_names_.txt
ethnicity/data/chinese/first_names/first_names_.txt
ethnicity/data/chinese/full_names/full_names_.txt
ethnicity/data/chinese/last_names/last_names_.txt
ethnicity/data/english/first_names/first_names_.txt
ethnicity/data/english/full_names/full_names_.txt
ethnicity/data/english/last_names/last_names_.txt
ethnicity/data/english/last_names_common/last_names_common_.txt
ethnicity/data/fijian/first_names/first_names_.txt
ethnicity/data/fijian/full_names/full_names_.txt
ethnicity/data/fijian/last_names/last_names_.txt
ethnicity/data/german/first_names/first_names_.txt
ethnicity/data/german/full_names/full_names_.txt
ethnicity/data/german/last_names/last_names_.txt
ethnicity/data/german/last_names_common/last_names_common_.txt
ethnicity/data/greek/first_names/first_names_.txt
ethnicity/data/greek/full_names/full_names_.txt
ethnicity/data/greek/last_names/last_names_.txt
ethnicity/data/greek/last_names_common/last_names_common_.txt
ethnicity/data/hawaiian/first_names/first_names_.txt
ethnicity/data/hawaiian/last_names/last_names_.txt
ethnicity/data/hispanic/first_names/first_names_.txt
ethnicity/data/hispanic/full_names/full_names_.txt
ethnicity/data/hispanic/last_names/last_names_.txt
ethnicity/data/hispanic/last_names_common/last_names_common_.txt
ethnicity/data/indian/first_names/first_names_.txt
ethnicity/data/indian/full_names/full_names_.txt
ethnicity/data/indian/last_names/last_names_.txt
ethnicity-0.0.20.dist-info/METADATA
ethnicity-0.0.20.dist-info/RECORD
ethnicity-0.0.20.dist-info/WHEEL
ethnicity-0.0.20.dist-info/top_level.txt
