Metadata-Version: 2.1
Name: ethnicity
Version: 0.0.20
Summary: Get ethnicity from name
Home-page: https://github.com/eeghor/ethnicity
Author: Igor Korostil
Author-email: eeghor@gmail.com
License: MIT
Keywords: ethnicity name
Platform: UNKNOWN
Classifier: Development Status :: 3 - Alpha
Classifier: Programming Language :: Python :: 3.6
Classifier: Topic :: Text Processing
Classifier: Topic :: Text Processing :: Filters
Requires-Python: >=3.6
Requires-Dist: pandas
